[
  {
    "title": "Grand Hotel",
    "year": 1932,
    "director": {
      "name": "Edmund Goulding",
      "imdb_person_url": "https://www.imdb.com/name/nm0332630/"
    },
    "production_studio": "Metro-Goldwyn-Mayer (MGM)",
    "mpaa_rating": "Passed",
    "runtime_minutes": 112,
    "budget_usd_millions": 0.7,
    "gross_revenue_usd_millions": 2.6,
    "ratings": {
      "imdb": 7.4,
      "rotten_tomatoes_critic": "86%",
      "rotten_tomatoes_popcorn": "79%"
    },
    "genres": [
      "Drama",
      "Romance"
    ],
    "actors": [
      {
        "name": "Greta Garbo",
        "imdb_person_url": "https://www.imdb.com/name/nm0001256/"
      },
      {
        "name": "John Barrymore",
        "imdb_person_url": "https://www.imdb.com/name/nm0000860/"
      },
      {
        "name": "Joan Crawford",
        "imdb_person_url": "https://www.imdb.com/name/nm0001076/"
      }
    ],
    "oscars_nominated": 1,
    "oscars_won": 1,
    "oscars_won_details": [
      "Best Picture"
    ],
    "description": "A group of very different individuals staying at a luxurious hotel in Berlin deal with each of their respective dramas.",
    "afi_ranking": null,
    "imdb_url": "https://www.imdb.com/title/tt0022958/",
    "rotten_tomatoes_url": "https://www.rottentomatoes.com/m/grand_hotel"
  },
  {
    "title": "Scarface",
    "year": 1932,
    "director": {
      "name": "Howard Hawks",
      "imdb_person_url": "https://www.imdb.com/name/nm0001328/"
    },
    "production_studio": "The Caddo Company",
    "mpaa_rating": "Passed",
    "runtime_minutes": 93,
    "budget_usd_millions": 0.6,
    "gross_revenue_usd_millions": 1,
    "ratings": {
      "imdb": 7.7,
      "rotten_tomatoes_critic": "98%",
      "rotten_tomatoes_popcorn": "88%"
    },
    "genres": [
      "Action",
      "Crime",
      "Drama"
    ],
    "actors": [
      {
        "name": "Paul Muni",
        "imdb_person_url": "https://www.imdb.com/name/nm0612868/"
      },
      {
        "name": "Ann Dvorak",
        "imdb_person_url": "https://www.imdb.com/name/nm0245464/"
      },
      {
        "name": "Karen Morley",
        "imdb_person_url": "https://www.imdb.com/name/nm0605629/"
      }
    ],
    "oscars_nominated": 1,
    "oscars_won": 0,
    "oscars_won_details": [],
    "description": "An ambitious and ruthless gangster rises to the top of the Chicago underworld.",
    "afi_ranking": null,
    "imdb_url": "https://www.imdb.com/title/tt0023427/",
    "rotten_tomatoes_url": "https://www.rottentomatoes.com/m/1018335-scarface"
  },
  {
    "title": "I Am a Fugitive from a Chain Gang",
    "year": 1932,
    "director": {
      "name": "Mervyn LeRoy",
      "imdb_person_url": "https://www.imdb.com/name/nm0504141/"
    },
    "production_studio": "Warner Bros.",
    "mpaa_rating": "Passed",
    "runtime_minutes": 93,
    "budget_usd_millions": 0.189,
    "gross_revenue_usd_millions": 0.65,
    "ratings": {
      "imdb": 8.0,
      "rotten_tomatoes_critic": "96%",
      "rotten_tomatoes_popcorn": "88%"
    },
    "genres": [
      "Crime",
      "Drama",
      "Film-Noir"
    ],
    "actors": [
      {
        "name": "Paul Muni",
        "imdb_person_url": "https://www.imdb.com/name/nm0612868/"
      },
      {
        "name": "Glenda Farrell",
        "imdb_person_url": "https://www.imdb.com/name/nm0268153/"
      },
      {
        "name": "Helen Vinson",
        "imdb_person_url": "https://www.imdb.com/name/nm0899017/"
      }
    ],
    "oscars_nominated": 3,
    "oscars_won": 0,
    "oscars_won_details": [],
    "description": "A World War I veteran is wrongly convicted of a crime and sentenced to a brutal Southern chain gang, from which he escapes.",
    "afi_ranking": null,
    "imdb_url": "https://www.imdb.com/title/tt0023042/",
    "rotten_tomatoes_url": "https://www.rottentomatoes.com/m/i_am_a_fugitive_from_a_chain_gang"
  },
  {
    "title": "Shanghai Express",
    "year": 1932,
    "director": {
      "name": "Josef von Sternberg",
      "imdb_person_url": "https://www.imdb.com/name/nm0903212/"
    },
    "production_studio": "Paramount Pictures",
    "mpaa_rating": "Passed",
    "runtime_minutes": 82,
    "budget_usd_millions": 0.8,
    "gross_revenue_usd_millions": 3.7,
    "ratings": {
      "imdb": 7.3,
      "rotten_tomatoes_critic": "93%",
      "rotten_tomatoes_popcorn": "81%"
    },
    "genres": [
      "Adventure",
      "Drama",
      "Romance"
    ],
    "actors": [
      {
        "name": "Marlene Dietrich",
        "imdb_person_url": "https://www.imdb.com/name/nm0000017/"
      },
      {
        "name": "Clive Brook",
        "imdb_person_url": "https://www.imdb.com/name/nm0111663/"
      },
      {
        "name": "Anna May Wong",
        "imdb_person_url": "https://www.imdb.com/name/nm0938923/"
      }
    ],
    "oscars_nominated": 3,
    "oscars_won": 1,
    "oscars_won_details": [
      "Best Cinematography"
    ],
    "description": "The passengers on a train traveling through revolutionary China are taken hostage by a warlord.",
    "afi_ranking": null,
    "imdb_url": "https://www.imdb.com/title/tt0023458/",
    "rotten_tomatoes_url": "https://www.rottentomatoes.com/m/shanghai_express"
  },
  {
    "title": "Freaks",
    "year": 1932,
    "director": {
      "name": "Tod Browning",
      "imdb_person_url": "https://www.imdb.com/name/nm0115316/"
    },
    "production_studio": "Metro-Goldwyn-Mayer (MGM)",
    "mpaa_rating": "Not Rated",
    "runtime_minutes": 64,
    "budget_usd_millions": 0.316,
    "gross_revenue_usd_millions": null,
    "ratings": {
      "imdb": 7.8,
      "rotten_tomatoes_critic": "95%",
      "rotten_tomatoes_popcorn": "86%"
    },
    "genres": [
      "Drama",
      "Horror"
    ],
    "actors": [
      {
        "name": "Wallace Ford",
        "imdb_person_url": "https://www.imdb.com/name/nm0285741/"
      },
      {
        "name": "Leila Hyams",
        "imdb_person_url": "https://www.imdb.com/name/nm0404886/"
      },
      {
        "name": "Olga Baclanova",
        "imdb_person_url": "https://www.imdb.com/name/nm0045507/"
      }
    ],
    "oscars_nominated": 0,
    "oscars_won": 0,
    "oscars_won_details": [],
    "description": "A circus' beautiful trapeze artist agrees to marry the leader of side-show performers, but her deformed friends discover she is only after his inheritance.",
    "afi_ranking": null,
    "imdb_url": "https://www.imdb.com/title/tt0022893/",
    "rotten_tomatoes_url": "https://www.rottentomatoes.com/m/freaks"
  },
  {
    "title": "Trouble in Paradise",
    "year": 1932,
    "director": {
      "name": "Ernst Lubitsch",
      "imdb_person_url": "https://www.imdb.com/name/nm0523932/"
    },
    "production_studio": "Paramount Pictures",
    "mpaa_rating": "Passed",
    "runtime_minutes": 83,
    "budget_usd_millions": 0.519,
    "gross_revenue_usd_millions": null,
    "ratings": {
      "imdb": 7.9,
      "rotten_tomatoes_critic": "91%",
      "rotten_tomatoes_popcorn": "89%"
    },
    "genres": [
      "Comedy",
      "Crime",
      "Romance"
    ],
    "actors": [
      {
        "name": "Miriam Hopkins",
        "imdb_person_url": "https://www.imdb.com/name/nm0001360/"
      },
      {
        "name": "Kay Francis",
        "imdb_person_url": "https://www.imdb.com/name/nm0290234/"
      },
      {
        "name": "Herbert Marshall",
        "imdb_person_url": "https://www.imdb.com/name/nm0551017/"
      }
    ],
    "oscars_nominated": 0,
    "oscars_won": 0,
    "oscars_won_details": [],
    "description": "A gentleman thief and his lovely partner team up to con a beautiful perfume company owner. Complications arise when the thief and the owner fall in love.",
    "afi_ranking": null,
    "imdb_url": "https://www.imdb.com/title/tt0023622/",
    "rotten_tomatoes_url": "https://www.rottentomatoes.com/m/trouble_in_paradise"
  },
  {
    "title": "The Mummy",
    "year": 1932,
    "director": {
      "name": "Karl Freund",
      "imdb_person_url": "https://www.imdb.com/name/nm0002086/"
    },
    "production_studio": "Universal Pictures",
    "mpaa_rating": "Passed",
    "runtime_minutes": 73,
    "budget_usd_millions": 0.196,
    "gross_revenue_usd_millions": null,
    "ratings": {
      "imdb": 7.0,
      "rotten_tomatoes_critic": "88%",
      "rotten_tomatoes_popcorn": "74%"
    },
    "genres": [
      "Fantasy",
      "Horror"
    ],
    "actors": [
      {
        "name": "Boris Karloff",
        "imdb_person_url": "https://www.imdb.com/name/nm0000472/"
      },
      {
        "name": "Zita Johann",
        "imdb_person_url": "https://www.imdb.com/name/nm0423548/"
      },
      {
        "name": "David Manners",
        "imdb_person_url": "https://www.imdb.com/name/nm0543142/"
      }
    ],
    "oscars_nominated": 0,
    "oscars_won": 0,
    "oscars_won_details": [],
    "description": "A resurrected Egyptian mummy stalks a beautiful woman he believes to be the reincarnation of his long-lost love.",
    "afi_ranking": null,
    "imdb_url": "https://www.imdb.com/title/tt0023245/",
    "rotten_tomatoes_url": "https://www.rottentomatoes.com/m/1014389-mummy"
  },
  {
    "title": "A Farewell to Arms",
    "year": 1932,
    "director": {
      "name": "Frank Borzage",
      "imdb_person_url": "https://www.imdb.com/name/nm0097645/"
    },
    "production_studio": "Paramount Pictures",
    "mpaa_rating": "Passed",
    "runtime_minutes": 80,
    "budget_usd_millions": 0.9,
    "gross_revenue_usd_millions": null,
    "ratings": {
      "imdb": 6.5,
      "rotten_tomatoes_critic": "77%",
      "rotten_tomatoes_popcorn": "56%"
    },
    "genres": [
      "Drama",
      "Romance",
      "War"
    ],
    "actors": [
      {
        "name": "Helen Hayes",
        "imdb_person_url": "https://www.imdb.com/name/nm0001331/"
      },
      {
        "name": "Gary Cooper",
        "imdb_person_url": "https://www.imdb.com/name/nm0000011/"
      },
      {
        "name": "Adolphe Menjou",
        "imdb_person_url": "https://www.imdb.com/name/nm0579634/"
      }
    ],
    "oscars_nominated": 4,
    "oscars_won": 2,
    "oscars_won_details": [
      "Best Cinematography",
      "Best Sound, Recording"
    ],
    "description": "An American ambulance driver and an English nurse fall in love in Italy during World War I.",
    "afi_ranking": null,
    "imdb_url": "https://www.imdb.com/title/tt0022879/",
    "rotten_tomatoes_url": "https://www.rottentomatoes.com/m/1007033-farewell_to_arms"
  },
  {
    "title": "The Old Dark House",
    "year": 1932,
    "director": {
      "name": "James Whale",
      "imdb_person_url": "https://www.imdb.com/name/nm0923762/"
    },
    "production_studio": "Universal Pictures",
    "mpaa_rating": "Not Rated",
    "runtime_minutes": 72,
    "budget_usd_millions": 0.25,
    "gross_revenue_usd_millions": null,
    "ratings": {
      "imdb": 7.1,
      "rotten_tomatoes_critic": "97%",
      "rotten_tomatoes_popcorn": "76%"
    },
    "genres": [
      "Comedy",
      "Horror",
      "Thriller"
    ],
    "actors": [
      {
        "name": "Boris Karloff",
        "imdb_person_url": "https://www.imdb.com/name/nm0000472/"
      },
      {
        "name": "Melvyn Douglas",
        "imdb_person_url": "https://www.imdb.com/name/nm0002048/"
      },
      {
        "name": "Charles Laughton",
        "imdb_person_url": "https://www.imdb.com/name/nm0001452/"
      }
    ],
    "oscars_nominated": 0,
    "oscars_won": 0,
    "oscars_won_details": [],
    "description": "Seeking shelter from a storm, five travelers are in for a bizarre and terrifying night when they stumble upon the Femm family home.",
    "afi_ranking": null,
    "imdb_url": "https://www.imdb.com/title/tt0023293/",
    "rotten_tomatoes_url": "https://www.rottentomatoes.com/m/the_old_dark_house"
  },
  {
    "title": "Love Me Tonight",
    "year": 1932,
    "director": {
      "name": "Rouben Mamoulian",
      "imdb_person_url": "https://www.imdb.com/name/nm0541240/"
    },
    "production_studio": "Paramount Pictures",
    "mpaa_rating": "Passed",
    "runtime_minutes": 88,
    "budget_usd_millions": 0.775,
    "gross_revenue_usd_millions": null,
    "ratings": {
      "imdb": 7.7,
      "rotten_tomatoes_critic": "100%",
      "rotten_tomatoes_popcorn": "86%"
    },
    "genres": [
      "Comedy",
      "Musical",
      "Romance"
    ],
    "actors": [
      {
        "name": "Maurice Chevalier",
        "imdb_person_url": "https://www.imdb.com/name/nm0002001/"
      },
      {
        "name": "Jeanette MacDonald",
        "imdb_person_url": "https://www.imdb.com/name/nm0531776/"
      },
      {
        "name": "Charles Ruggles",
        "imdb_person_url": "https://www.imdb.com/name/nm0749459/"
      }
    ],
    "oscars_nominated": 0,
    "oscars_won": 0,
    "oscars_won_details": [],
    "description": "A Parisian tailor poses as a baron and falls in love with a princess, with complications ensuing.",
    "afi_ranking": null,
    "imdb_url": "https://www.imdb.com/title/tt0023158/",
    "rotten_tomatoes_url": "https://www.rottentomatoes.com/m/love_me_tonight"
  },
  {
    "title": "Horse Feathers",
    "year": 1932,
    "director": {
      "name": "Norman Z. McLeod",
      "imdb_person_url": "https://www.imdb.com/name/nm0572855/"
    },
    "production_studio": "Paramount Pictures",
    "mpaa_rating": "Passed",
    "runtime_minutes": 68,
    "budget_usd_millions": null,
    "gross_revenue_usd_millions": null,
    "ratings": {
      "imdb": 7.4,
      "rotten_tomatoes_critic": "86%",
      "rotten_tomatoes_popcorn": "86%"
    },
    "genres": [
      "Comedy",
      "Musical",
      "Sport"
    ],
    "actors": [
      {
        "name": "Groucho Marx",
        "imdb_person_url": "https://www.imdb.com/name/nm0000050/"
      },
      {
        "name": "Harpo Marx",
        "imdb_person_url": "https://www.imdb.com/name/nm0555621/"
      },
      {
        "name": "Chico Marx",
        "imdb_person_url": "https://www.imdb.com/name/nm0555611/"
      }
    ],
    "oscars_nominated": 0,
    "oscars_won": 0,
    "oscars_won_details": [],
    "description": "A college president tries to improve his school's football team by hiring two inept professional players.",
    "afi_ranking": 65,
    "imdb_url": "https://www.imdb.com/title/tt0023027/",
    "rotten_tomatoes_url": "https://www.rottentomatoes.com/m/horse_feathers"
  },
  {
    "title": "The Most Dangerous Game",
    "year": 1932,
    "director": {
      "name": "Irving Pichel",
      "imdb_person_url": "https://www.imdb.com/name/nm0681729/"
    },
    "production_studio": "RKO Radio Pictures",
    "mpaa_rating": "Passed",
    "runtime_minutes": 63,
    "budget_usd_millions": 0.218,
    "gross_revenue_usd_millions": null,
    "ratings": {
      "imdb": 7.5,
      "rotten_tomatoes_critic": "100%",
      "rotten_tomatoes_popcorn": "79%"
    },
    "genres": [
      "Adventure",
      "Horror",
      "Thriller"
    ],
    "actors": [
      {
        "name": "Joel McCrea",
        "imdb_person_url": "https://www.imdb.com/name/nm0001520/"
      },
      {
        "name": "Fay Wray",
        "imdb_person_url": "https://www.imdb.com/name/nm0942102/"
      },
      {
        "name": "Leslie Banks",
        "imdb_person_url": "https://www.imdb.com/name/nm0052187/"
      }
    ],
    "oscars_nominated": 0,
    "oscars_won": 0,
    "oscars_won_details": [],
    "description": "A big-game hunter on a remote island decides to hunt the ultimate prey: man.",
    "afi_ranking": null,
    "imdb_url": "https://www.imdb.com/title/tt0023238/",
    "rotten_tomatoes_url": "https://www.rottentomatoes.com/m/the_most_dangerous_game_1932"
  },
  {
    "title": "Red Dust",
    "year": 1932,
    "director": {
      "name": "Victor Fleming",
      "imdb_person_url": "https://www.imdb.com/name/nm0002078/"
    },
    "production_studio": "Metro-Goldwyn-Mayer (MGM)",
    "mpaa_rating": "Passed",
    "runtime_minutes": 83,
    "budget_usd_millions": 0.408,
    "gross_revenue_usd_millions": 2.2,
    "ratings": {
      "imdb": 7.4,
      "rotten_tomatoes_critic": "100%",
      "rotten_tomatoes_popcorn": "80%"
    },
    "genres": [
      "Drama",
      "Romance"
    ],
    "actors": [
      {
        "name": "Clark Gable",
        "imdb_person_url": "https://www.imdb.com/name/nm0000022/"
      },
      {
        "name": "Jean Harlow",
        "imdb_person_url": "https://www.imdb.com/name/nm0001318/"
      },
      {
        "name": "Gene Raymond",
        "imdb_person_url": "https://www.imdb.com/name/nm0713217/"
      }
    ],
    "oscars_nominated": 0,
    "oscars_won": 0,
    "oscars_won_details": [],
    "description": "On a rubber plantation in French Indochina, the plantation owner is torn between a married woman and a prostitute.",
    "afi_ranking": null,
    "imdb_url": "https://www.imdb.com/title/tt0023389/",
    "rotten_tomatoes_url": "https://www.rottentomatoes.com/m/red_dust"
  },
  {
    "title": "Vampyr",
    "year": 1932,
    "director": {
      "name": "Carl Theodor Dreyer",
      "imdb_person_url": "https://www.imdb.com/name/nm0002052/"
    },
    "production_studio": "Tobis Filmkunst",
    "mpaa_rating": "Not Rated",
    "runtime_minutes": 75,
    "budget_usd_millions": null,
    "gross_revenue_usd_millions": null,
    "ratings": {
      "imdb": 7.5,
      "rotten_tomatoes_critic": "98%",
      "rotten_tomatoes_popcorn": "81%"
    },
    "genres": [
      "Fantasy",
      "Horror"
    ],
    "actors": [
      {
        "name": "Julian West",
        "imdb_person_url": "https://www.imdb.com/name/nm0922271/"
      },
      {
        "name": "Maurice Schutz",
        "imdb_person_url": "https://www.imdb.com/name/nm0776510/"
      },
      {
        "name": "Rena Mandel",
        "imdb_person_url": "https://www.imdb.com/name/nm0541785/"
      }
    ],
    "oscars_nominated": 0,
    "oscars_won": 0,
    "oscars_won_details": [],
    "description": "A traveler obsessed with the supernatural visits an old inn and finds himself in a village haunted by a vampire.",
    "afi_ranking": null,
    "imdb_url": "https://www.imdb.com/title/tt0023649/",
    "rotten_tomatoes_url": "https://www.rottentomatoes.com/m/vampyr"
  },
  {
    "title": "One Hour with You",
    "year": 1932,
    "director": {
      "name": "George Cukor",
      "imdb_person_url": "https://www.imdb.com/name/nm0002029/"
    },
    "production_studio": "Paramount Pictures",
    "mpaa_rating": "Passed",
    "runtime_minutes": 80,
    "budget_usd_millions": null,
    "gross_revenue_usd_millions": null,
    "ratings": {
      "imdb": 6.9,
      "rotten_tomatoes_critic": "92%",
      "rotten_tomatoes_popcorn": "72%"
    },
    "genres": [
      "Comedy",
      "Musical",
      "Romance"
    ],
    "actors": [
      {
        "name": "Maurice Chevalier",
        "imdb_person_url": "https://www.imdb.com/name/nm0002001/"
      },
      {
        "name": "Jeanette MacDonald",
        "imdb_person_url": "https://www.imdb.com/name/nm0531776/"
      },
      {
        "name": "Genevieve Tobin",
        "imdb_person_url": "https://www.imdb.com/name/nm0864903/"
      }
    ],
    "oscars_nominated": 1,
    "oscars_won": 0,
    "oscars_won_details": [],
    "description": "A Parisian doctor's fidelity to his wife is tested when her best friend makes a play for him.",
    "afi_ranking": null,
    "imdb_url": "https://www.imdb.com/title/tt0023299/",
    "rotten_tomatoes_url": "https://www.rottentomatoes.com/m/one_hour_with_you"
  },
  {
    "title": "Tarzan the Ape Man",
    "year": 1932,
    "director": {
      "name": "W.S. Van Dyke",
      "imdb_person_url": "https://www.imdb.com/name/nm0887852/"
    },
    "production_studio": "Metro-Goldwyn-Mayer (MGM)",
    "mpaa_rating": "Passed",
    "runtime_minutes": 100,
    "budget_usd_millions": 0.617,
    "gross_revenue_usd_millions": 2.5,
    "ratings": {
      "imdb": 7.0,
      "rotten_tomatoes_critic": "94%",
      "rotten_tomatoes_popcorn": "68%"
    },
    "genres": [
      "Action",
      "Adventure",
      "Romance"
    ],
    "actors": [
      {
        "name": "Johnny Weissmuller",
        "imdb_person_url": "https://www.imdb.com/name/nm0001835/"
      },
      {
        "name": "Maureen O'Sullivan",
        "imdb_person_url": "https://www.imdb.com/name/nm0001579/"
      },
      {
        "name": "Neil Hamilton",
        "imdb_person_url": "https://www.imdb.com/name/nm0358045/"
      }
    ],
    "oscars_nominated": 0,
    "oscars_won": 0,
    "oscars_won_details": [],
    "description": "A man raised by apes in the African jungle falls in love with a woman from a safari expedition.",
    "afi_ranking": null,
    "imdb_url": "https://www.imdb.com/title/tt0023551/",
    "rotten_tomatoes_url": "https://www.rottentomatoes.com/m/tarzan_the_ape_man"
  },
  {
    "title": "The Sign of the Cross",
    "year": 1932,
    "director": {
      "name": "Cecil B. DeMille",
      "imdb_person_url": "https://www.imdb.com/name/nm0001124/"
    },
    "production_studio": "Paramount Pictures",
    "mpaa_rating": "Passed",
    "runtime_minutes": 125,
    "budget_usd_millions": 0.65,
    "gross_revenue_usd_millions": null,
    "ratings": {
      "imdb": 6.8,
      "rotten_tomatoes_critic": "86%",
      "rotten_tomatoes_popcorn": "65%"
    },
    "genres": [
      "Adventure",
      "Drama",
      "History"
    ],
    "actors": [
      {
        "name": "Fredric March",
        "imdb_person_url": "https://www.imdb.com/name/nm0545214/"
      },
      {
        "name": "Elissa Landi",
        "imdb_person_url": "https://www.imdb.com/name/nm0484730/"
      },
      {
        "name": "Claudette Colbert",
        "imdb_person_url": "https://www.imdb.com/name/nm0001055/"
      }
    ],
    "oscars_nominated": 1,
    "oscars_won": 0,
    "oscars_won_details": [],
    "description": "In ancient Rome, a Roman prefect falls in love with a Christian woman and is torn between his love for her and his loyalty to the emperor.",
    "afi_ranking": null,
    "imdb_url": "https://www.imdb.com/title/tt0023478/",
    "rotten_tomatoes_url": "https://www.rottentomatoes.com/m/the_sign_of_the_cross"
  },
  {
    "title": "Red-Headed Woman",
    "year": 1932,
    "director": {
      "name": "Jack Conway",
      "imdb_person_url": "https://www.imdb.com/name/nm0176840/"
    },
    "production_studio": "Metro-Goldwyn-Mayer (MGM)",
    "mpaa_rating": "Passed",
    "runtime_minutes": 79,
    "budget_usd_millions": 0.4,
    "gross_revenue_usd_millions": 1.1,
    "ratings": {
      "imdb": 7.0,
      "rotten_tomatoes_critic": "100%",
      "rotten_tomatoes_popcorn": "73%"
    },
    "genres": [
      "Comedy",
      "Romance"
    ],
    "actors": [
      {
        "name": "Jean Harlow",
        "imdb_person_url": "https://www.imdb.com/name/nm0001318/"
      },
      {
        "name": "Chester Morris",
        "imdb_person_url": "https://www.imdb.com/name/nm0606410/"
      },
      {
        "name": "Lewis Stone",
        "imdb_person_url": "https://www.imdb.com/name/nm0832168/"
      }
    ],
    "oscars_nominated": 0,
    "oscars_won": 0,
    "oscars_won_details": [],
    "description": "An ambitious and amoral woman sleeps her way to the top of the social ladder.",
    "afi_ranking": null,
    "imdb_url": "https://www.imdb.com/title/tt0023391/",
    "rotten_tomatoes_url": "https://www.rottentomatoes.com/m/redheaded_woman"
  },
  {
    "title": "The Mask of Fu Manchu",
    "year": 1932,
    "director": {
      "name": "Charles Brabin",
      "imdb_person_url": "https://www.imdb.com/name/nm0102657/"
    },
    "production_studio": "Metro-Goldwyn-Mayer (MGM)",
    "mpaa_rating": "Passed",
    "runtime_minutes": 68,
    "budget_usd_millions": 0.32,
    "gross_revenue_usd_millions": 0.5,
    "ratings": {
      "imdb": 6.8,
      "rotten_tomatoes_critic": "93%",
      "rotten_tomatoes_popcorn": "65%"
    },
    "genres": [
      "Adventure",
      "Horror",
      "Sci-Fi"
    ],
    "actors": [
      {
        "name": "Boris Karloff",
        "imdb_person_url": "https://www.imdb.com/name/nm0000472/"
      },
      {
        "name": "Lewis Stone",
        "imdb_person_url": "https://www.imdb.com/name/nm0832168/"
      },
      {
        "name": "Karen Morley",
        "imdb_person_url": "https://www.imdb.com/name/nm0605629/"
      }
    ],
    "oscars_nominated": 0,
    "oscars_won": 0,
    "oscars_won_details": [],
    "description": "A British expedition to find the tomb of Genghis Khan is opposed by the evil Dr. Fu Manchu.",
    "afi_ranking": null,
    "imdb_url": "https://www.imdb.com/title/tt0023201/",
    "rotten_tomatoes_url": "https://www.rottentomatoes.com/m/the_mask_of_fu_manchu"
  },
  {
    "title": "White Zombie",
    "year": 1932,
    "director": {
      "name": "Victor Halperin",
      "imdb_person_url": "https://www.imdb.com/name/nm0355416/"
    },
    "production_studio": "United Artists",
    "mpaa_rating": "Passed",
    "runtime_minutes": 69,
    "budget_usd_millions": 0.05,
    "gross_revenue_usd_millions": null,
    "ratings": {
      "imdb": 6.3,
      "rotten_tomatoes_critic": "86%",
      "rotten_tomatoes_popcorn": "45%"
    },
    "genres": [
      "Horror"
    ],
    "actors": [
      {
        "name": "Bela Lugosi",
        "imdb_person_url": "https://www.imdb.com/name/nm0000509/"
      },
      {
        "name": "Madge Bellamy",
        "imdb_person_url": "https://www.imdb.com/name/nm0068536/"
      },
      {
        "name": "Joseph Cawthorn",
        "imdb_person_url": "https://www.imdb.com/name/nm0147253/"
      }
    ],
    "oscars_nominated": 0,
    "oscars_won": 0,
    "oscars_won_details": [],
    "description": "A young man turns to a witch doctor to lure the woman he loves away from her fiancé, but instead turns her into a zombie slave.",
    "afi_ranking": null,
    "imdb_url": "https://www.imdb.com/title/tt0023694/",
    "rotten_tomatoes_url": "https://www.rottentomatoes.com/m/white_zombie"
  },
  {
    "title": "The Music Box",
    "year": 1932,
    "director": {
      "name": "James Parrott",
      "imdb_person_url": "https://www.imdb.com/name/nm0663459/"
    },
    "production_studio": "Hal Roach Studios",
    "mpaa_rating": "Not Rated",
    "runtime_minutes": 29,
    "budget_usd_millions": null,
    "gross_revenue_usd_millions": null,
    "ratings": {
      "imdb": 7.9,
      "rotten_tomatoes_critic": "100%",
      "rotten_tomatoes_popcorn": "86%"
    },
    "genres": [
      "Comedy",
      "Short"
    ],
    "actors": [
      {
        "name": "Stan Laurel",
        "imdb_person_url": "https://www.imdb.com/name/nm0001453/"
      },
      {
        "name": "Oliver Hardy",
        "imdb_person_url": "https://www.imdb.com/name/nm0001316/"
      },
      {
        "name": "Billy Gilbert",
        "imdb_person_url": "https://www.imdb.com/name/nm0318080/"
      }
    ],
    "oscars_nominated": 1,
    "oscars_won": 1,
    "oscars_won_details": [
      "Best Short Subject, Comedy"
    ],
    "description": "Two bumbling delivery men have a series of misadventures while trying to deliver a piano.",
    "afi_ranking": null,
    "imdb_url": "https://www.imdb.com/title/tt0023251/",
    "rotten_tomatoes_url": "https://www.rottentomatoes.com/m/the_music_box"
  },
  {
    "title": "Flowers and Trees",
    "year": 1932,
    "director": {
      "name": "Burt Gillett",
      "imdb_person_url": "https://www.imdb.com/name/nm0318536/"
    },
    "production_studio": "Walt Disney Productions",
    "mpaa_rating": "Not Rated",
    "runtime_minutes": 8,
    "budget_usd_millions": null,
    "gross_revenue_usd_millions": null,
    "ratings": {
      "imdb": 7.3,
      "rotten_tomatoes_critic": "100%",
      "rotten_tomatoes_popcorn": "76%"
    },
    "genres": [
      "Animation",
      "Short",
      "Comedy"
    ],
    "actors": [],
    "oscars_nominated": 1,
    "oscars_won": 1,
    "oscars_won_details": [
      "Best Short Subject, Cartoons"
    ],
    "description": "A charming animated short in which trees and flowers come to life.",
    "afi_ranking": null,
    "imdb_url": "https://www.imdb.com/title/tt0022899/",
    "rotten_tomatoes_url": "https://www.rottentomatoes.com/m/flowers_and_trees"
  },
  {
    "title": "One Way Passage",
    "year": 1932,
    "director": {
      "name": "Tay Garnett",
      "imdb_person_url": "https://www.imdb.com/name/nm0307828/"
    },
    "production_studio": "Warner Bros.",
    "mpaa_rating": "Passed",
    "runtime_minutes": 67,
    "budget_usd_millions": null,
    "gross_revenue_usd_millions": null,
    "ratings": {
      "imdb": 7.4,
      "rotten_tomatoes_critic": "94%",
      "rotten_tomatoes_popcorn": "79%"
    },
    "genres": [
      "Drama",
      "Romance"
    ],
    "actors": [
      {
        "name": "William Powell",
        "imdb_person_url": "https://www.imdb.com/name/nm0001635/"
      },
      {
        "name": "Kay Francis",
        "imdb_person_url": "https://www.imdb.com/name/nm0290234/"
      },
      {
        "name": "Aline MacMahon",
        "imdb_person_url": "https://www.imdb.com/name/nm0534062/"
      }
    ],
    "oscars_nominated": 1,
    "oscars_won": 1,
    "oscars_won_details": [
      "Best Writing, Original Story"
    ],
    "description": "On an ocean liner, a condemned murderer and a terminally ill woman fall in love, each unaware of the other's secret.",
    "afi_ranking": null,
    "imdb_url": "https://www.imdb.com/title/tt0023308/",
    "rotten_tomatoes_url": "https://www.rottentomatoes.com/m/one_way_passage"
  },
  {
    "title": "The Crowd Roars",
    "year": 1932,
    "director": {
      "name": "Howard Hawks",
      "imdb_person_url": "https://www.imdb.com/name/nm0001328/"
    },
    "production_studio": "Warner Bros.",
    "mpaa_rating": "Passed",
    "runtime_minutes": 70,
    "budget_usd_millions": null,
    "gross_revenue_usd_millions": null,
    "ratings": {
      "imdb": 6.8,
      "rotten_tomatoes_critic": "86%",
      "rotten_tomatoes_popcorn": "65%"
    },
    "genres": [
      "Action",
      "Drama",
      "Sport"
    ],
    "actors": [
      {
        "name": "James Cagney",
        "imdb_person_url": "https://www.imdb.com/name/nm0000010/"
      },
      {
        "name": "Joan Blondell",
        "imdb_person_url": "https://www.imdb.com/name/nm0000951/"
      },
      {
        "name": "Ann Dvorak",
        "imdb_person_url": "https://www.imdb.com/name/nm0245464/"
      }
    ],
    "oscars_nominated": 0,
    "oscars_won": 0,
    "oscars_won_details": [],
    "description": "A champion race car driver tries to protect his younger brother from the dangers of the sport.",
    "afi_ranking": null,
    "imdb_url": "https://www.imdb.com/title/tt0022791/",
    "rotten_tomatoes_url": "https://www.rottentomatoes.com/m/1004791-crowd_roars"
  }
]
